vauth/__init__.py
vauth/__main__.py
vauth/commands.py
vauth/database.py
vauth/encryption.py
vauth/handlers.py
vauth-0.0.6.data/scripts/vauth
vauth-0.0.6.dist-info/METADATA
vauth-0.0.6.dist-info/WHEEL
vauth-0.0.6.dist-info/entry_points.txt
vauth-0.0.6.dist-info/top_level.txt
vauth-0.0.6.dist-info/RECORD
