Metadata-Version: 2.1
Name: vauth
Version: 0.0.6
Summary: A simple 2-factor-authentication client
Home-page: https://github.com/theofficialvedantjoshi/vAUTH
Author: Vedant Joshi
Classifier: Programming Language :: Python :: 3
Classifier: License :: OSI Approved :: MIT License
Classifier: Operating System :: OS Independent
Requires-Python: >=3.6
Requires-Dist: pyotp
Requires-Dist: qrcode
Requires-Dist: cryptography
Requires-Dist: keyboard
